sonusai_asr_sensory/__init__.py
sonusai_asr_sensory/asr_functions/__init__.py
sonusai_asr_sensory/asr_functions/sensory.py
sonusai_asr_sensory-0.2.0.dist-info/METADATA
sonusai_asr_sensory-0.2.0.dist-info/WHEEL
sonusai_asr_sensory-0.2.0.dist-info/RECORD
